setup.py
common/__init__.py
common/decos.py
common/descrptrs.py
common/errors.py
common/metaclasses.py
common/utils.py
common/variables.py
gb_messenger_server.egg-info/PKG-INFO
gb_messenger_server.egg-info/SOURCES.txt
gb_messenger_server.egg-info/dependency_links.txt
gb_messenger_server.egg-info/requires.txt
gb_messenger_server.egg-info/top_level.txt
logs/__init__.py
logs/config_server_log.py
server/__init__.py
server/add_user.py
server/config_window.py
server/core.py
server/database.py
server/main_window.py
server/remove_user.py
server/stat_window.py
unit_tests/__init__.py