Metadata-Version: 1.0
Name: gb-messenger-server
Version: 0.0.1
Summary: gb_messenger_server
Home-page: UNKNOWN
Author: Anatolii Tsirkunenko
Author-email: tsirkunenkoat@gmail.com
License: UNKNOWN
Platform: UNKNOWN
